kafka/__init__.py
kafka/client_async.py
kafka/cluster.py
kafka/codec.py
kafka/conn.py
kafka/errors.py
kafka/future.py
kafka/socks5_wrapper.py
kafka/structs.py
kafka/util.py
kafka/version.py
kafka/admin/__init__.py
kafka/admin/acl_resource.py
kafka/admin/client.py
kafka/admin/config_resource.py
kafka/admin/new_partitions.py
kafka/admin/new_topic.py
kafka/benchmarks/__init__.py
kafka/benchmarks/consumer_performance.py
kafka/benchmarks/load_example.py
kafka/benchmarks/producer_performance.py
kafka/benchmarks/record_batch_compose.py
kafka/benchmarks/record_batch_read.py
kafka/benchmarks/varint_speed.py
kafka/consumer/__init__.py
kafka/consumer/fetcher.py
kafka/consumer/group.py
kafka/consumer/subscription_state.py
kafka/coordinator/__init__.py
kafka/coordinator/base.py
kafka/coordinator/consumer.py
kafka/coordinator/heartbeat.py
kafka/coordinator/protocol.py
kafka/coordinator/assignors/__init__.py
kafka/coordinator/assignors/abstract.py
kafka/coordinator/assignors/range.py
kafka/coordinator/assignors/roundrobin.py
kafka/coordinator/assignors/sticky/__init__.py
kafka/coordinator/assignors/sticky/partition_movements.py
kafka/coordinator/assignors/sticky/sorted_set.py
kafka/coordinator/assignors/sticky/sticky_assignor.py
kafka/metrics/__init__.py
kafka/metrics/compound_stat.py
kafka/metrics/dict_reporter.py
kafka/metrics/kafka_metric.py
kafka/metrics/measurable.py
kafka/metrics/measurable_stat.py
kafka/metrics/metric_config.py
kafka/metrics/metric_name.py
kafka/metrics/metrics.py
kafka/metrics/metrics_reporter.py
kafka/metrics/quota.py
kafka/metrics/stat.py
kafka/metrics/stats/__init__.py
kafka/metrics/stats/avg.py
kafka/metrics/stats/count.py
kafka/metrics/stats/histogram.py
kafka/metrics/stats/max_stat.py
kafka/metrics/stats/min_stat.py
kafka/metrics/stats/percentile.py
kafka/metrics/stats/percentiles.py
kafka/metrics/stats/rate.py
kafka/metrics/stats/sampled_stat.py
kafka/metrics/stats/sensor.py
kafka/metrics/stats/total.py
kafka/partitioner/__init__.py
kafka_python-2.2.5.dist-info/METADATA
kafka_python-2.2.5.dist-info/WHEEL
kafka_python-2.2.5.dist-info/top_level.txt
kafka_python-2.2.5.dist-info/RECORD
