Metadata-Version: 2.4
Name: kafka-python
Version: 2.2.5
Summary: Pure Python client for Apache Kafka
Author-email: Dana Powers <dana.powers@gmail.com>
Project-URL: Homepage, https://github.com/dpkp/kafka-python
Keywords: apache kafka,kafka
Classifier: Development Status :: 5 - Production/Stable
Classifier: Intended Audience :: Developers
Classifier: License :: OSI Approved :: Apache Software License
Classifier: Programming Language :: Python
Classifier: Programming Language :: Python :: 2
Classifier: Programming Language :: Python :: 2.7
Classifier: Programming Language :: Python :: 3
Classifier: Programming Language :: Python :: 3.4
Classifier: Programming Language :: Python :: 3.5
Classifier: Programming Language :: Python :: 3.6
Classifier: Programming Language :: Python :: 3.7
Classifier: Programming Language :: Python :: 3.8
Classifier: Programming Language :: Python :: 3.9
Classifier: Programming Language :: Python :: 3.10
Classifier: Programming Language :: Python :: 3.11
Classifier: Programming Language :: Python :: 3.12
Classifier: Programming Language :: Python :: 3.13
Classifier: Programming Language :: Python :: Implementation :: CPython
Classifier: Programming Language :: Python :: Implementation :: PyPy
Classifier: Topic :: Software Development :: Libraries :: Python Modules
Provides-Extra: crc32c
Requires-Dist: crc32c; extra == "crc32c"
Provides-Extra: lz4
Requires-Dist: lz4; extra == "lz4"
Provides-Extra: snappy
Requires-Dist: python-snappy; extra == "snappy"
Provides-Extra: zstd
Requires-Dist: zstandard; extra == "zstd"
Provides-Extra: testing
Requires-Dist: pytest; extra == "testing"
Requires-Dist: mock; python_version < "3.3" and extra == "testing"
Requires-Dist: pytest-mock; extra == "testing"
Requires-Dist: pytest-timeout; extra == "testing"
Provides-Extra: benchmarks
Requires-Dist: pyperf; extra == "benchmarks"
